.bumpversion.cfg
.gitignore
.gitmodules
.travis.yml
COPYING
README.md
README.rst
amazon.py
example.py
requirements.in
requirements.txt
setup.py
wercker.yml
docs/.gitignore
docs/Makefile
docs/source/_templates
docs/source/conf.py
docs/source/index.rst
docs/source/_static/image.png
rgmining_amazon_dataset.egg-info/PKG-INFO
rgmining_amazon_dataset.egg-info/SOURCES.txt
rgmining_amazon_dataset.egg-info/dependency_links.txt
rgmining_amazon_dataset.egg-info/requires.txt
rgmining_amazon_dataset.egg-info/top_level.txt
tests/__init__.py
tests/amazon_test.py
tests/test_suite.py